hypothesis_bio/__init__.py
hypothesis_bio/strategies.py
hypothesis_bio-0.1.dist-info/LICENSE
hypothesis_bio-0.1.dist-info/WHEEL
hypothesis_bio-0.1.dist-info/METADATA
hypothesis_bio-0.1.dist-info/RECORD
