Metadata-Version: 2.1
Name: hypothesis-bio
Version: 0.1
Summary: Hypothesis strategies for biological data
Home-page: https://github.com/luizirber/hypothesis-bio
License: UNKNOWN
Author: Luiz Irber
Author-email: contact@luizirber.org
Requires-Python: >=3.5
Classifier: Development Status :: 4 - Beta
Classifier: Framework :: Hypothesis
Classifier: License :: OSI Approved :: MIT License
Classifier: Intended Audience :: Developers
Classifier: Programming Language :: Python
Classifier: Programming Language :: Python :: 3
Classifier: Programming Language :: Python :: 3.5
Classifier: Programming Language :: Python :: 3.6
Classifier: Programming Language :: Python :: 3.7
Classifier: Topic :: Software Development :: Testing
Requires-Dist: hypothesis >= 4.0.0
Requires-Dist: sphinx >= 2.0.0, < 3; extra == "docs"
Requires-Dist: pygments-github-lexers >= 0.0.5; extra == "docs"
Requires-Dist: sphinxcontrib-autoprogram >= 0.1.5; extra == "docs"
Requires-Dist: pytest >=2.7.3; extra == "testing"
Requires-Dist: pytest-cov; extra == "testing"
Provides-Extra: docs
Provides-Extra: testing
